odoo/addons/purchase_stock_picking_actual_date_show_currency_rate/README.rst
odoo/addons/purchase_stock_picking_actual_date_show_currency_rate/__init__.py
odoo/addons/purchase_stock_picking_actual_date_show_currency_rate/__manifest__.py
odoo/addons/purchase_stock_picking_actual_date_show_currency_rate/i18n/purchase_stock_picking_actual_date_show_currency_rate.pot
odoo/addons/purchase_stock_picking_actual_date_show_currency_rate/models/__init__.py
odoo/addons/purchase_stock_picking_actual_date_show_currency_rate/models/stock_picking.py
odoo/addons/purchase_stock_picking_actual_date_show_currency_rate/readme/CONTRIBUTORS.rst
odoo/addons/purchase_stock_picking_actual_date_show_currency_rate/readme/DESCRIPTION.rst
odoo/addons/purchase_stock_picking_actual_date_show_currency_rate/static/description/icon.png
odoo/addons/purchase_stock_picking_actual_date_show_currency_rate/static/description/index.html
odoo/addons/purchase_stock_picking_actual_date_show_currency_rate/tests/__init__.py
odoo/addons/purchase_stock_picking_actual_date_show_currency_rate/tests/test_purchase_stock_picking.py
odoo_addon_purchase_stock_picking_actual_date_show_currency_rate-16.0.1.0.0.2.dist-info/METADATA
odoo_addon_purchase_stock_picking_actual_date_show_currency_rate-16.0.1.0.0.2.dist-info/WHEEL
odoo_addon_purchase_stock_picking_actual_date_show_currency_rate-16.0.1.0.0.2.dist-info/top_level.txt
odoo_addon_purchase_stock_picking_actual_date_show_currency_rate-16.0.1.0.0.2.dist-info/RECORD
