Metadata-Version: 2.1
Name: odoo-addon-purchase_stock_picking_actual_date_show_currency_rate
Version: 16.0.1.0.0.2
Summary: Purchase Stock Picking Actual Date Show Currency Rate
Home-page: https://github.com/OCA/purchase-workflow
Author: Quartile, Odoo Community Association (OCA)
Author-email: support@odoo-community.org
License: AGPL-3
Classifier: Programming Language :: Python
Classifier: Framework :: Odoo
Classifier: Framework :: Odoo :: 16.0
Classifier: License :: OSI Approved :: GNU Affero General Public License v3
Requires-Python: >=3.10
Requires-Dist: odoo-addon-purchase-stock-picking-show-currency-rate<16.1dev,>=16.0dev
Requires-Dist: odoo-addon-stock-move-actual-date<16.1dev,>=16.0dev
Requires-Dist: odoo<16.1dev,>=16.0a
